README.rst
setup.py
win10note/__init__.py
win10note.egg-info/PKG-INFO
win10note.egg-info/SOURCES.txt
win10note.egg-info/dependency_links.txt
win10note.egg-info/requires.txt
win10note.egg-info/top_level.txt